.gitignore
LICENSE
README.md
setup.py
tscounters/__init__.py
tscounters/aggregator.py
tscounters/counter_engine.py
tscounters/counter_pusher.py
tscounters/counters.py
tscounters_py.egg-info/PKG-INFO
tscounters_py.egg-info/SOURCES.txt
tscounters_py.egg-info/dependency_links.txt
tscounters_py.egg-info/requires.txt
tscounters_py.egg-info/top_level.txt