Metadata-Version: 1.0
Name: tscounters-py
Version: 0.0.3
Summary: Time-series counters
Home-page: https://github.com/jiaxincao/tscounters-py
Author: Jiaxin Cao
Author-email: Jiaxin.Cao@gmail.com
License: UNKNOWN
Keywords: opentsdb,metrics,counters
Platform: UNKNOWN
